CHANGES.txt
LICENSE.txt
MANIFEST.in
README.txt
setup.py
net_conf/__init__.py
net_conf/exceptions.py
net_conf/providers.py
net_conf/scanners.py
net_conf/utils.py
net_conf/wifi.py
net_conf.egg-info/PKG-INFO
net_conf.egg-info/SOURCES.txt
net_conf.egg-info/dependency_links.txt
net_conf.egg-info/requires.txt
net_conf.egg-info/top_level.txt