Metadata-Version: 1.0
Name: net-conf
Version: 0.2.1
Summary: Commandline-based network manager
Home-page: http://pypi.python.org/pypi/net_conf/
Author: Brian Wiborg
Author-email: baccenfutter@c-base.org
License: LICENSE.txt
Platform: UNKNOWN
